mcp_sharepoint/__init__.py
mcp_sharepoint/common.py
mcp_sharepoint/resources.py
mcp_sharepoint/server.py
mcp_sharepoint/tools.py
mcp_sharepoint-0.1.7.dist-info/licenses/LICENSE
mcp_sharepoint-0.1.7.dist-info/METADATA
mcp_sharepoint-0.1.7.dist-info/WHEEL
mcp_sharepoint-0.1.7.dist-info/entry_points.txt
mcp_sharepoint-0.1.7.dist-info/top_level.txt
mcp_sharepoint-0.1.7.dist-info/RECORD
