Metadata-Version: 2.4
Name: mcp-sharepoint
Version: 0.1.7
Summary: MCP Server to integrate with SharePoint
Author: sofias tech
Requires-Python: >=3.10
License-File: LICENSE
Requires-Dist: mcp>=1.2.1
Requires-Dist: office365-rest-python-client>=2.6.1
Requires-Dist: python-dotenv>=1.0.0
Requires-Dist: pymupdf>=1.23.0
Requires-Dist: pandas>=2.0.0
Requires-Dist: openpyxl>=3.1.0
Requires-Dist: python-docx>=1.1.0
Dynamic: license-file
